disnake/ext/fluent/__init__.py
disnake/ext/fluent/fluent.py
disnake/ext/fluent/py.typed
disnake/ext/fluent/types.py
disnake/ext/fluent/utils.py
disnake_ext_fluent-0.1.1.dist-info/METADATA
disnake_ext_fluent-0.1.1.dist-info/WHEEL
disnake_ext_fluent-0.1.1.dist-info/licenses/LICENSE
disnake_ext_fluent-0.1.1.dist-info/RECORD
